upgxl/__init__.py
upgxl/pgxl.py
upgxl-0.0.5.dist-info/METADATA
upgxl-0.0.5.dist-info/WHEEL
upgxl-0.0.5.dist-info/licenses/LICENSE.md
upgxl-0.0.5.dist-info/RECORD
